synch_FIFO/FIFO.v
module fifo(input clk,
            input rst,
            input w_en,
            input r_en,
            input [7:0] din,
            output reg [7:0] dout,
            output full,
            output empty);

    reg [7:0] memory [0:15]; //16 rows each having 8 bits

    //5-bit pointers (4 bits for addressing 0-15 and 1 bit for flags)
    reg [4:0] w_ptr;
    reg [4:0] r_ptr;

    //Write logic
    always @(posedge clk) begin
        if (rst) w_ptr <= 5'b0;
        else if (w_en && !full) begin
            memory[ w_ptr[3:0] ] <= din; //Lower 4 bits for memory indexing
            w_ptr <= w_ptr+1;
        end
    end

    //Read logic
    always @(posedge clk) begin
        if (rst) begin
            r_ptr <= 5'b0;
            dout <= 8'b0;
        end
        else if (r_en && !empty) begin
            dout <= memory[ r_ptr[3:0] ]; //Lower 4 bits for memory indexing
            r_ptr <= r_ptr+1;
        end
    end

    //Empty logic
    assign empty = (w_ptr == r_ptr);

    //Full logic
    assign full = (w_ptr[4] != r_ptr[4]) && (w_ptr[3:0] == r_ptr[3:0]);

endmodule

synch_FIFO/testbench.v
`timescale 1ns/1ps

module fifo_tb();
    //Inputs of UUT
    reg clk;
    reg rst;
    reg w_en;
    reg r_en;
    reg [7:0] din;

    //Outputs of UUT
    wire [7:0] dout;
    wire full;
    wire empty;

    fifo uut(
        .clk(clk),
        .rst(rst),
        .w_en(w_en),
        .r_en(r_en),
        .din(din),
        .dout(dout),
        .full(full),
        .empty(empty)
    );

    always begin
        #5 clk = ~clk;
    end

    integer i;

    initial begin
        //Initialization
        clk = 0;
        rst = 1;
        w_en = 0;
        r_en = 0;
        din = 8'b0;

        #10
        rst = 0;
        #5

        w_en = 1;
        for(i = 0; i <= 16; i = i+1) begin
            din = i;
            #10;
        end
        w_en = 0;
        #10

        r_en = 1;
        for(i = 0; i <= 16; i = i+1) begin
            #10;
        end
        r_en = 0;
        #10

        w_en = 1;
        for(i = 0; i <= 16; i = i+1) begin
            din = i+16;
            #10;
        end
        w_en = 0;

        #20
        $finish;
    end

    initial begin
        $monitor("Time=%0t | rst=%b | w_en=%b | din=%h | r_en=%b | dout=%h | full=%b | empty=%b",
                $time, rst, w_en, din, r_en, dout, full, empty);
        $dumpfile("waveform.vcd");
        $dumpvars(0, fifo_tb);
    end
endmodule

synch_FIFO/waveform.vcd
$date
	Tue May 26 23:27:55 2026
$end
$version
	Icarus Verilog
$end
$timescale
	1ps
$end
$scope module fifo_tb $end
$var wire 1 ! full $end
$var wire 1 " empty $end
$var wire 8 # dout [7:0] $end
$var reg 1 $ clk $end
$var reg 8 % din [7:0] $end
$var reg 1 & r_en $end
$var reg 1 ' rst $end
$var reg 1 ( w_en $end
$var integer 32 ) i [31:0] $end
$scope module uut $end
$var wire 1 $ clk $end
$var wire 8 * din [7:0] $end
$var wire 1 ! full $end
$var wire 1 & r_en $end
$var wire 1 ' rst $end
$var wire 1 ( w_en $end
$var wire 1 " empty $end
$var reg 8 + dout [7:0] $end
$var reg 5 , r_ptr [4:0] $end
$var reg 5 - w_ptr [4:0] $end
$upscope $end
$upscope $end
$enddefinitions $end
$comment Show the parameter values. $end
$dumpall
$end
#0
$dumpvars
bx -
bx ,
bx +
b0 *
bx )
0(
1'
0&
b0 %
0$
bx #
x"
x!
$end
#5000
0!
1"
b0 -
b0 #
b0 +
b0 ,
1$
#10000
0$
0'
#15000
0"
b1 -
1$
b0 )
1(
#20000
0$
#25000
b10 -
1$
b1 %
b1 *
b1 )
#30000
0$
#35000
b11 -
1$
b10 %
b10 *
b10 )
#40000
0$
#45000
b100 -
1$
b11 %
b11 *
b11 )
#50000
0$
#55000
b101 -
1$
b100 %
b100 *
b100 )
#60000
0$
#65000
b110 -
1$
b101 %
b101 *
b101 )
#70000
0$
#75000
b111 -
1$
b110 %
b110 *
b110 )
#80000
0$
#85000
b1000 -
1$
b111 %
b111 *
b111 )
#90000
0$
#95000
b1001 -
1$
b1000 %
b1000 *
b1000 )
#100000
0$
#105000
b1010 -
1$
b1001 %
b1001 *
b1001 )
#110000
0$
#115000
b1011 -
1$
b1010 %
b1010 *
b1010 )
#120000
0$
#125000
b1100 -
1$
b1011 %
b1011 *
b1011 )
#130000
0$
#135000
b1101 -
1$
b1100 %
b1100 *
b1100 )
#140000
0$
#145000
b1110 -
1$
b1101 %
b1101 *
b1101 )
#150000
0$
#155000
b1111 -
1$
b1110 %
b1110 *
b1110 )
#160000
0$
#165000
1!
b10000 -
1$
b1111 %
b1111 *
b1111 )
#170000
0$
#175000
1$
b10000 %
b10000 *
b10000 )
#180000
0$
#185000
1$
0(
b10001 )
#190000
0$
#195000
0!
b1 ,
1$
b0 )
1&
#200000
0$
#205000
b10 ,
b1 #
b1 +
1$
b1 )
#210000
0$
#215000
b11 ,
b10 #
b10 +
1$
b10 )
#220000
0$
#225000
b100 ,
b11 #
b11 +
1$
b11 )
#230000
0$
#235000
b101 ,
b100 #
b100 +
1$
b100 )
#240000
0$
#245000
b110 ,
b101 #
b101 +
1$
b101 )
#250000
0$
#255000
b111 ,
b110 #
b110 +
1$
b110 )
#260000
0$
#265000
b1000 ,
b111 #
b111 +
1$
b111 )
#270000
0$
#275000
b1001 ,
b1000 #
b1000 +
1$
b1000 )
#280000
0$
#285000
b1010 ,
b1001 #
b1001 +
1$
b1001 )
#290000
0$
#295000
b1011 ,
b1010 #
b1010 +
1$
b1010 )
#300000
0$
#305000
b1100 ,
b1011 #
b1011 +
1$
b1011 )
#310000
0$
#315000
b1101 ,
b1100 #
b1100 +
1$
b1100 )
#320000
0$
#325000
b1110 ,
b1101 #
b1101 +
1$
b1101 )
#330000
0$
#335000
b1111 ,
b1110 #
b1110 +
1$
b1110 )
#340000
0$
#345000
0!
1"
b10000 ,
b1111 #
b1111 +
1$
b1111 )
#350000
0$
#355000
1$
b10000 )
#360000
0$
#365000
1$
0&
b10001 )
#370000
0$
#375000
0"
b10001 -
1$
b0 )
1(
#380000
0$
#385000
b10010 -
1$
b10001 %
b10001 *
b1 )
#390000
0$
#395000
b10011 -
1$
b10010 %
b10010 *
b10 )
#400000
0$
#405000
b10100 -
1$
b10011 %
b10011 *
b11 )
#410000
0$
#415000
b10101 -
1$
b10100 %
b10100 *
b100 )
#420000
0$
#425000
b10110 -
1$
b10101 %
b10101 *
b101 )
#430000
0$
#435000
b10111 -
1$
b10110 %
b10110 *
b110 )
#440000
0$
#445000
b11000 -
1$
b10111 %
b10111 *
b111 )
#450000
0$
#455000
b11001 -
1$
b11000 %
b11000 *
b1000 )
#460000
0$
#465000
b11010 -
1$
b11001 %
b11001 *
b1001 )
#470000
0$
#475000
b11011 -
1$
b11010 %
b11010 *
b1010 )
#480000
0$
#485000
b11100 -
1$
b11011 %
b11011 *
b1011 )
#490000
0$
#495000
b11101 -
1$
b11100 %
b11100 *
b1100 )
#500000
0$
#505000
b11110 -
1$
b11101 %
b11101 *
b1101 )
#510000
0$
#515000
b11111 -
1$
b11110 %
b11110 *
b1110 )
#520000
0$
#525000
1!
b0 -
1$
b11111 %
b11111 *
b1111 )
#530000
0$
#535000
1$
b100000 %
b100000 *
b10000 )
#540000
0$
#545000
1$
0(
b10001 )
