asynch_FIFO/read_ctrl.v
module r_ctrl(input rclk,
                 input rrst,
                 input r_en,
                 input [4:0] rq2_wptr,
                 output reg rempty,
                 output [3:0] raddr,
                 output reg [4:0] rptr);
    
    reg [4:0] rbin;
    wire [4:0] rbin_next;
    wire [4:0] rgray_next;
    wire rempty_val;

    always @(posedge rclk or posedge rrst) begin
        if (rrst) begin
            rbin <= 5'b0;
            rptr <= 5'b0;
        end
        else begin
            rbin <= rbin_next;
            rptr <= rgray_next;
        end
    end

    assign rbin_next = rbin + (r_en && !rempty); //Pointer increment logic

    assign rgray_next = rbin_next ^ (rbin_next>>1); //Binary to Gray code conversion

    assign raddr = rptr[3:0]; //Bit slicing the lower 4 bits

    assign rempty_val = (rgray_next == rq2_wptr); //Combinational calculation of flag

    //Updating flag in the next clock cycle (Sequential part)
    always @(posedge rclk or posedge rrst) begin
        if (rrst) rempty <= 1;
        else rempty <= rempty_val;
    end

endmodule

asynch_FIFO/write_ctrl.v
module w_ctrl(input wclk,
                  input wrst,
                  input w_en,
                  input [4:0] wq2_rptr,
                  output reg wfull,
                  output [3:0] waddr,
                  output reg [4:0] wptr);

    reg [4:0] wbin;
    wire [4:0] wbin_next;
    wire [4:0] wgray_next;
    wire wfull_value;

    always @(posedge wclk or posedge wrst) begin
        if (wrst) begin
            wbin <= 5'b0;
            wptr <= 5'b0;
        end
        else begin
            wbin <= wbin_next;
            wptr <= wgray_next;
        end
    end

    assign wbin_next = wbin + (w_en && !wfull); //Pointer increment logic

    assign wgray_next = wbin_next ^ (wbin_next>>1); //Binary to Gray code conversion

    assign waddr = wptr[3:0]; //Bit slicing the lower 4 bits

    assign wfull_value = (wgray_next[4] != wq2_rptr[4]) && (wgray_next[3:0] == wq2_rptr[3:0]); //Combinational calculation of flag

    //Updating flag in the next clock cycle (Sequential part)
    always @(posedge wclk or posedge wrst) begin
        if (wrst) wfull <= 0;
        else wfull <= wfull_value;
    end
endmodule

asynch_FIFO/ptr_synch.v
module synchronizer(input clk,
                 input rst,
                 input [4:0] ptr_in,
                 output reg [4:0] ptr_out);

    reg [4:0] q1_ptr;

    always @(posedge clk or posedge rst) begin
        if (rst) begin
            q1_ptr <= 5'b0;
            ptr_out <= 5'b0;
        end
        else begin
            q1_ptr <= ptr_in; //2-stage pointer synchronizer (2 flip flops)
            ptr_out <= q1_ptr;
        end
    end
endmodule

asynch_FIFO/memory.v
module mem(input wclk,
            input wclken,
            input [3:0] waddr,
            input [7:0] din,
            input rclk,
            input [3:0] raddr,
            output [7:0] dout);

    reg [7:0] memory_array [0:15];

    always @(posedge wclk) begin
        if (wclken) memory_array[waddr] <= din;
    end

    assign dout = memory_array[raddr];

endmodule

asynch_FIFO/topmodule.v
module Top(input wclk,
           input wrst,
           input w_en,
           input [7:0] din,
           output wfull,
           
           input rclk,
           input rrst,
           input r_en,
           output [7:0] dout,
           output rempty);

    wire [4:0] wptr, rptr;
    wire [4:0] wq2_rptr, rq2_wptr;
    wire [3:0] waddr, raddr;

    // Memory
    mem memory_core(
        .wclk(wclk),
        .wclken(w_en & !wfull),
        .waddr(waddr),
        .din(din),
        .rclk(rclk),
        .raddr(raddr),
        .dout(dout)
    );

    // Synchronizing rptr into write clock domain
    synchronizer rsynch(
        .clk(wclk),
        .rst(wrst),
        .ptr_in(rptr),
        .ptr_out(wq2_rptr)
    );

    // Synchronizing wptr into read clock domain
    synchronizer wsynch(
        .clk(rclk),
        .rst(rrst),
        .ptr_in(wptr),
        .ptr_out(rq2_wptr)
    );

    // Write logic
    w_ctrl write(
        .wclk(wclk),
        .wrst(wrst),
        .w_en(w_en),
        .wq2_rptr(wq2_rptr),
        .wfull(wfull),
        .waddr(waddr),
        .wptr(wptr)
    );

    //Read logic
    r_ctrl read(
        .rclk(rclk),
        .rrst(rrst),
        .r_en(r_en),
        .rq2_wptr(rq2_wptr),
        .rempty(rempty),
        .raddr(raddr),
        .rptr(rptr)
    );

endmodule

asynch_FIFO/testbench.v
`timescale 1ns/1ps

module fifo_tb();
    // Inputs of UUT
    reg wclk;
    reg wrst;
    reg w_en;
    reg [7:0] din;
    reg rclk;
    reg rrst;
    reg r_en;

    // Outputs of UUT
    wire wfull;
    wire [7:0] dout;
    wire rempty;

    Top uut(
        .wclk(wclk),
        .wrst(wrst),
        .w_en(w_en),
        .din(din),
        .wfull(wfull),
        .rclk(rclk),
        .rrst(rrst),
        .r_en(r_en),
        .dout(dout),
        .rempty(rempty)
    );

    //Write clock (Time period = 10ns)
    always begin
        #5 wclk = ~wclk;
    end

    //Read clock (Time period = 15 ns)
    always begin
        #7.5 rclk = ~rclk;
    end

    integer i;
    initial begin
        // Initialization
        wclk = 0;
        wrst = 1;
        w_en = 0;
        rclk = 0;
        rrst = 1;
        r_en = 0;
        din = 8'b0;

        #30
        wrst = 0;
        rrst = 0;
        #10

        w_en = 1;
        for (i = 0; i <= 16; i = i+1) begin
            din = i;
            #10;
        end
        w_en = 0;
        #10

        r_en = 1;
        for (i = 0; i <= 16; i = i+1) begin
            #10;
        end
        r_en = 0;
        #10

        w_en = 1;
        for (i = 0; i <= 16; i = i+1) begin
            din = i+16;
            #10;
        end
        w_en=0;

        #20
        $finish;
    end

    initial begin
        $monitor("Time=%0t | wclk=%b | rclk=%b | wrst=%b | rrst=%b | w_en=%b | din=%h | r_en=%b | dout=%h | wfull=%b | rempty=%b",
                $time, wclk, rclk, wrst, rrst, w_en, din, r_en, dout, wfull, rempty);
        $dumpfile("waveform.vcd");
        $dumpvars(0, fifo_tb);
    end
endmodule

asynch_FIFO/waveform.vcd
$date
	Sat May 30 04:58:25 2026
$end
$version
	Icarus Verilog
$end
$timescale
	1ps
$end
$scope module fifo_tb $end
$var wire 1 ! wfull $end
$var wire 1 " rempty $end
$var wire 8 # dout [7:0] $end
$var reg 8 $ din [7:0] $end
$var reg 1 % r_en $end
$var reg 1 & rclk $end
$var reg 1 ' rrst $end
$var reg 1 ( w_en $end
$var reg 1 ) wclk $end
$var reg 1 * wrst $end
$var integer 32 + i [31:0] $end
$scope module uut $end
$var wire 8 , din [7:0] $end
$var wire 1 % r_en $end
$var wire 1 & rclk $end
$var wire 1 ' rrst $end
$var wire 1 ( w_en $end
$var wire 1 ) wclk $end
$var wire 1 * wrst $end
$var wire 5 - wq2_rptr [4:0] $end
$var wire 5 . wptr [4:0] $end
$var wire 1 ! wfull $end
$var wire 4 / waddr [3:0] $end
$var wire 5 0 rq2_wptr [4:0] $end
$var wire 5 1 rptr [4:0] $end
$var wire 1 " rempty $end
$var wire 4 2 raddr [3:0] $end
$var wire 8 3 dout [7:0] $end
$scope module memory_core $end
$var wire 8 4 din [7:0] $end
$var wire 8 5 dout [7:0] $end
$var wire 1 & rclk $end
$var wire 1 ) wclk $end
$var wire 1 6 wclken $end
$var wire 4 7 waddr [3:0] $end
$var wire 4 8 raddr [3:0] $end
$upscope $end
$scope module read $end
$var wire 1 % r_en $end
$var wire 1 & rclk $end
$var wire 5 9 rgray_next [4:0] $end
$var wire 1 ' rrst $end
$var wire 5 : rq2_wptr [4:0] $end
$var wire 1 ; rempty_val $end
$var wire 5 < rbin_next [4:0] $end
$var wire 4 = raddr [3:0] $end
$var reg 5 > rbin [4:0] $end
$var reg 1 " rempty $end
$var reg 5 ? rptr [4:0] $end
$upscope $end
$scope module rsynch $end
$var wire 1 ) clk $end
$var wire 5 @ ptr_in [4:0] $end
$var wire 1 * rst $end
$var reg 5 A ptr_out [4:0] $end
$var reg 5 B q1_ptr [4:0] $end
$upscope $end
$scope module write $end
$var wire 1 ( w_en $end
$var wire 1 ) wclk $end
$var wire 1 C wfull_value $end
$var wire 5 D wgray_next [4:0] $end
$var wire 5 E wq2_rptr [4:0] $end
$var wire 1 * wrst $end
$var wire 5 F wbin_next [4:0] $end
$var wire 4 G waddr [3:0] $end
$var reg 5 H wbin [4:0] $end
$var reg 1 ! wfull $end
$var reg 5 I wptr [4:0] $end
$upscope $end
$scope module wsynch $end
$var wire 1 & clk $end
$var wire 5 J ptr_in [4:0] $end
$var wire 1 ' rst $end
$var reg 5 K ptr_out [4:0] $end
$var reg 5 L q1_ptr [4:0] $end
$upscope $end
$upscope $end
$upscope $end
$enddefinitions $end
$comment Show the parameter values. $end
$dumpall
$end
#0
$dumpvars
b0 L
b0 K
b0 J
b0 I
b0 H
b0 G
b0 F
b0 E
b0 D
0C
b0 B
b0 A
b0 @
b0 ?
b0 >
b0 =
b0 <
1;
b0 :
b0 9
b0 8
b0 7
06
bx 5
b0 4
bx 3
b0 2
b0 1
b0 0
b0 /
b0 .
b0 -
b0 ,
bx +
1*
0)
0(
1'
0&
0%
b0 $
bx #
1"
0!
$end
#5000
1)
#7500
1&
#10000
0)
#15000
1)
0&
#20000
0)
#22500
1&
#25000
1)
#30000
0)
0&
0'
0*
#35000
1)
#37500
1&
#40000
b1 D
16
b1 F
0)
b0 +
1(
#45000
b1 /
b1 7
b1 G
b11 D
b0 #
b0 3
b0 5
b1 .
b1 I
b1 J
b10 F
b1 H
1)
0&
#50000
0)
b1 $
b1 ,
b1 4
b1 +
#52500
b1 L
1&
#55000
b11 /
b11 7
b11 G
b10 D
b11 .
b11 I
b11 J
b11 F
b10 H
1)
#60000
0)
0&
b10 $
b10 ,
b10 4
b10 +
#65000
b10 /
b10 7
b10 G
b110 D
b10 .
b10 I
b10 J
b100 F
b11 H
1)
#67500
0;
b1 0
b1 :
b1 K
b10 L
1&
#70000
0)
b11 $
b11 ,
b11 4
b11 +
#75000
b110 /
b110 7
b110 G
b111 D
b110 .
b110 I
b110 J
b101 F
b100 H
1)
0&
#80000
0)
b100 $
b100 ,
b100 4
b100 +
#82500
b10 0
b10 :
b10 K
b110 L
0"
1&
#85000
b111 /
b111 7
b111 G
b101 D
b111 .
b111 I
b111 J
b110 F
b101 H
1)
#90000
0)
0&
b101 $
b101 ,
b101 4
b101 +
#95000
b101 /
b101 7
b101 G
b100 D
b101 .
b101 I
b101 J
b111 F
b110 H
1)
#97500
b110 0
b110 :
b110 K
b101 L
1&
#100000
0)
b110 $
b110 ,
b110 4
b110 +
#105000
b100 /
b100 7
b100 G
b1100 D
b100 .
b100 I
b100 J
b1000 F
b111 H
1)
0&
#110000
0)
b111 $
b111 ,
b111 4
b111 +
#112500
b101 0
b101 :
b101 K
b100 L
1&
#115000
b1100 /
b1100 7
b1100 G
b1101 D
b1100 .
b1100 I
b1100 J
b1001 F
b1000 H
1)
#120000
0)
0&
b1000 $
b1000 ,
b1000 4
b1000 +
#125000
b1101 /
b1101 7
b1101 G
b1111 D
b1101 .
b1101 I
b1101 J
b1010 F
b1001 H
1)
#127500
b100 0
b100 :
b100 K
b1101 L
1&
#130000
0)
b1001 $
b1001 ,
b1001 4
b1001 +
#135000
b1111 /
b1111 7
b1111 G
b1110 D
b1111 .
b1111 I
b1111 J
b1011 F
b1010 H
1)
0&
#140000
0)
b1010 $
b1010 ,
b1010 4
b1010 +
#142500
b1101 0
b1101 :
b1101 K
b1111 L
1&
#145000
b1110 /
b1110 7
b1110 G
b1010 D
b1110 .
b1110 I
b1110 J
b1100 F
b1011 H
1)
#150000
0)
0&
b1011 $
b1011 ,
b1011 4
b1011 +
#155000
b1010 /
b1010 7
b1010 G
b1011 D
b1010 .
b1010 I
b1010 J
b1101 F
b1100 H
1)
#157500
b1111 0
b1111 :
b1111 K
b1010 L
1&
#160000
0)
b1100 $
b1100 ,
b1100 4
b1100 +
#165000
b1011 /
b1011 7
b1011 G
b1001 D
b1011 .
b1011 I
b1011 J
b1110 F
b1101 H
1)
0&
#170000
0)
b1101 $
b1101 ,
b1101 4
b1101 +
#172500
b1010 0
b1010 :
b1010 K
b1011 L
1&
#175000
b1001 /
b1001 7
b1001 G
b1000 D
b1001 .
b1001 I
b1001 J
b1111 F
b1110 H
1)
#180000
0)
0&
b1110 $
b1110 ,
b1110 4
b1110 +
#185000
b1000 /
b1000 7
b1000 G
b11000 D
b1000 .
b1000 I
b1000 J
b10000 F
b1111 H
1)
#187500
b1011 0
b1011 :
b1011 K
b1000 L
1&
#190000
0)
b1111 $
b1111 ,
b1111 4
b1111 +
#195000
b11001 D
b11000 .
b11000 I
b11000 J
b10001 F
b10000 H
1)
0&
#200000
0)
b10000 $
b10000 ,
b10000 4
b10000 +
#202500
b1000 0
b1000 :
b1000 K
b11000 L
1&
#205000
b1001 /
b1001 7
b1001 G
b11011 D
b11001 .
b11001 I
b11001 J
b10010 F
b10001 H
1)
#210000
b11001 D
06
b10001 F
0)
0&
0(
b10001 +
#215000
1)
#217500
b11000 0
b11000 :
b11000 K
b11001 L
1&
#220000
b1 9
b1 <
0)
b0 +
1%
#225000
1)
0&
#230000
0)
b1 +
#232500
b1 #
b1 3
b1 5
b1 2
b1 8
b1 =
b11 9
b11001 0
b11001 :
b11001 K
b1 1
b1 ?
b1 @
b10 <
b1 >
1&
#235000
b1 B
1)
#240000
0)
0&
b10 +
#245000
b1 -
b1 A
b1 E
1)
#247500
b10 #
b10 3
b10 5
b11 2
b11 8
b11 =
b10 9
b11 1
b11 ?
b11 @
b11 <
b10 >
1&
#250000
0)
b11 +
#255000
b11 B
1)
0&
#260000
0)
b100 +
#262500
b11 #
b11 3
b11 5
b10 2
b10 8
b10 =
b110 9
b10 1
b10 ?
b10 @
b100 <
b11 >
1&
#265000
b11 -
b11 A
b11 E
b10 B
1)
#270000
0)
0&
b101 +
#275000
b10 -
b10 A
b10 E
1)
#277500
b100 #
b100 3
b100 5
b110 2
b110 8
b110 =
b111 9
b110 1
b110 ?
b110 @
b101 <
b100 >
1&
#280000
0)
b110 +
#285000
b110 B
1)
0&
#290000
0)
b111 +
#292500
b101 #
b101 3
b101 5
b111 2
b111 8
b111 =
b101 9
b111 1
b111 ?
b111 @
b110 <
b101 >
1&
#295000
b110 -
b110 A
b110 E
b111 B
1)
#300000
0)
0&
b1000 +
#305000
b111 -
b111 A
b111 E
1)
#307500
b110 #
b110 3
b110 5
b101 2
b101 8
b101 =
b100 9
b101 1
b101 ?
b101 @
b111 <
b110 >
1&
#310000
0)
b1001 +
#315000
b101 B
1)
0&
#320000
0)
b1010 +
#322500
b111 #
b111 3
b111 5
b100 2
b100 8
b100 =
b1100 9
b100 1
b100 ?
b100 @
b1000 <
b111 >
1&
#325000
b101 -
b101 A
b101 E
b100 B
1)
#330000
0)
0&
b1011 +
#335000
b100 -
b100 A
b100 E
1)
#337500
b1000 #
b1000 3
b1000 5
b1100 2
b1100 8
b1100 =
b1101 9
b1100 1
b1100 ?
b1100 @
b1001 <
b1000 >
1&
#340000
0)
b1100 +
#345000
b1100 B
1)
0&
#350000
0)
b1101 +
#352500
b1001 #
b1001 3
b1001 5
b1101 2
b1101 8
b1101 =
b1111 9
b1101 1
b1101 ?
b1101 @
b1010 <
b1001 >
1&
#355000
b1100 -
b1100 A
b1100 E
b1101 B
1)
#360000
0)
0&
b1110 +
#365000
b1101 -
b1101 A
b1101 E
1)
#367500
b1010 #
b1010 3
b1010 5
b1111 2
b1111 8
b1111 =
b1110 9
b1111 1
b1111 ?
b1111 @
b1011 <
b1010 >
1&
#370000
0)
b1111 +
#375000
b1111 B
1)
0&
#380000
0)
b10000 +
#382500
b1011 #
b1011 3
b1011 5
b1110 2
b1110 8
b1110 =
b1010 9
b1110 1
b1110 ?
b1110 @
b1100 <
b1011 >
1&
#385000
b1111 -
b1111 A
b1111 E
b1110 B
1)
#390000
b1110 9
b1011 <
0)
0&
0%
b10001 +
#395000
b1110 -
b1110 A
b1110 E
1)
#397500
1&
#400000
b11011 D
16
b10010 F
0)
b0 +
1(
#405000
b1011 /
b1011 7
b1011 G
b11010 D
b11011 .
b11011 I
b11011 J
b10011 F
b10010 H
1)
0&
#410000
0)
b10001 $
b10001 ,
b10001 4
b1 +
#412500
b11011 L
1&
#415000
1C
b1010 /
b1010 7
b1010 G
b11110 D
b11010 .
b11010 I
b11010 J
b10100 F
b10011 H
1)
#420000
0)
0&
b10010 $
b10010 ,
b10010 4
b10 +
#425000
1C
06
b1110 /
b1110 7
b1110 G
b11110 D
1!
b11110 .
b11110 I
b11110 J
b10100 F
b10100 H
1)
#427500
b11011 0
b11011 :
b11011 K
b11110 L
1&
#430000
0)
b10011 $
b10011 ,
b10011 4
b11 +
#435000
1)
0&
#440000
0)
b10100 $
b10100 ,
b10100 4
b100 +
#442500
b11110 0
b11110 :
b11110 K
1&
#445000
1)
#450000
0)
0&
b10101 $
b10101 ,
b10101 4
b101 +
#455000
1)
#457500
1&
#460000
0)
b10110 $
b10110 ,
b10110 4
b110 +
#465000
1)
0&
#470000
0)
b10111 $
b10111 ,
b10111 4
b111 +
#472500
1&
#475000
1)
#480000
0)
0&
b11000 $
b11000 ,
b11000 4
b1000 +
#485000
1)
#487500
1&
#490000
0)
b11001 $
b11001 ,
b11001 4
b1001 +
#495000
1)
0&
#500000
0)
b11010 $
b11010 ,
b11010 4
b1010 +
#502500
1&
#505000
1)
#510000
0)
0&
b11011 $
b11011 ,
b11011 4
b1011 +
#515000
1)
#517500
1&
#520000
0)
b11100 $
b11100 ,
b11100 4
b1100 +
#525000
1)
0&
#530000
0)
b11101 $
b11101 ,
b11101 4
b1101 +
#532500
1&
#535000
1)
#540000
0)
0&
b11110 $
b11110 ,
b11110 4
b1110 +
#545000
1)
#547500
1&
#550000
0)
b11111 $
b11111 ,
b11111 4
b1111 +
#555000
1)
0&
#560000
0)
b100000 $
b100000 ,
b100000 4
b10000 +
#562500
1&
#565000
1)
#570000
0)
0&
0(
b10001 +
